<odoo>
    <record id='form_wizard_precuenta' model="ir.ui.view">
        <field name="name">Wizard Precuenta</field>
        <field name="model">motgama.wizardprecuenta</field>
        <field name="arch" type="xml">
            <form string="Precuenta">
                <field name="incluye_ocasional" invisible="1"/>
                <field name="incluye_amanecida" invisible="1"/>
                <field name="incluye_adicional" invisible="1"/>
                <group>
                    <h2><span>Habitación</span>&amp;nbsp;<span><field name='habitacion' readonly="1"/></span></h2>
                    <field name="fecha_asignacion" readonly="1"/>
                </group>
                <group>
                    <field name="consumos" readonly="1">
                        <tree>
                            <field name="producto_id"/>
                            <field name="cantidad"/>
                            <field name="vlrUnitario"/>
                            <field name="vlrSubtotal"/>
                        </tree>
                    </field>
                    <field name="hospedaje_normal" readonly="1" attrs="{'invisible':[('incluye_ocasional','=',False)]}"/>
                    <field name="hospedaje_amanecida" readonly="1" attrs="{'invisible':[('incluye_amanecida','=',False)]}"/>
                    <field name="hospedaje_adicional" readonly="1" attrs="{'invisible':[('incluye_adicional','=',False)]}"/>
                </group>
                <group>
                    <field name="abono_ids">
                        <tree>
                            <field name="nrorecaudo"/>
                            <field name="create_date"/>
                            <field name="valor_pagado"/>
                        </tree>
                    </field>
                </group>
                <group>
                    <group>
                        <field name="valor_total" readonly="1"/>
                    </group>
                    <group>
                        <field name="abonado" readonly="1"/>
                    </group>
                </group>
                <group>
                    <field name="adeudado" readonly="1"/>
                </group>
                <footer>
                    <button string="Aceptar" special="cancel" class="btn btn-primary"/>
                </footer>
            </form>
        </field>
    </record>
</odoo>