<?xml version="1.0" encoding="utf-8"?>
<odoo>
<!--Tree                                                                                                              P7.0.4R -->
  <record id="tree_view_consumo" model="ir.ui.view">
    <field name="name">Consumos</field>
    <field name="model">motgama.consumo</field>
    <field name="limit">100</field>
    <field name="arch" type="xml">   
      <tree string="Consumo" editable="top" default_order='create_date desc'>
        <field name="recepcion" string="recepcion" invisible="1"/>
        <field name="llevaComanda" invisible="1"/>
        <field name="permitecambiarvalor" invisible="1"/>
        <field name="valorUnitario" invisible="1"/>
        <field name="habitacion" string="Habitacion" required="1" domain="[('estado','in',['OO','OA','LQ']),('recepcion','=',recepcion)]" options="{'no_create':True}"/>
        <field name="producto_id" string="Producto" required="1"/>
        <field name="lugar_id" string="Bodega de Inventario" required="1" domain="[('permite_consumo','=',True)]" options="{'no_create':True}"/>
        <field name="textoComanda" attrs="{'readonly':[('llevaComanda','=',False)],'required':[('llevaComanda','=',True)]}"/>
        <field name="vlrUnitario" string="Valor Unitario $" attrs="{'readonly':[('permitecambiarvalor','=',False)]}"/>
        <field name="cantidad" string="Cantidad" required="1"/>
        <field name="vlrSubtotal" string="Subtotal $"/>
      </tree>
    </field>
  </record>
</odoo>